capirca_xlate/__init__.py
capirca_xlate/templates/acl.pol.j2
capirca_xlate/templates/def.net.j2
capirca_xlate/templates/def.svc.j2
capirca_xlate/xlate.py
capirca_xlate-0.1.1.dist-info/METADATA
capirca_xlate-0.1.1.dist-info/WHEEL
capirca_xlate-0.1.1.dist-info/RECORD
