Metadata-Version: 2.1
Name: capirca-xlate
Version: 0.1.1
Summary: 
Author: Tyler Christiansen
Author-email: code@tylerc.me
Requires-Python: >=3.10,<4.0
Classifier: Programming Language :: Python :: 3
Classifier: Programming Language :: Python :: 3.10
Classifier: Programming Language :: Python :: 3.11
Requires-Dist: Jinja2 (>=3.1,<4.0)
Requires-Dist: ruamel.yaml (>=0.17,<0.18)
